pysafebrowsing/__init__.py
pysafebrowsing/about.py
pysafebrowsing/api.py
pysafebrowsing/cli.py
pysafebrowsing-0.1.3.dist-info/LICENSE
pysafebrowsing-0.1.3.dist-info/METADATA
pysafebrowsing-0.1.3.dist-info/WHEEL
pysafebrowsing-0.1.3.dist-info/entry_points.txt
pysafebrowsing-0.1.3.dist-info/top_level.txt
pysafebrowsing-0.1.3.dist-info/RECORD
