Metadata-Version: 2.1
Name: pysafebrowsing
Version: 0.1.3
Summary: Google Safe Browsing API python wrapper
Home-page: https://github.com/Te-k/pysafebrowsing
Author: Tek
Author-email: tek@randhome.io
License: MIT
Keywords: security
Classifier: Programming Language :: Python :: 3
Classifier: License :: OSI Approved :: MIT License
Classifier: Operating System :: OS Independent
License-File: LICENSE
Requires-Dist: requests (>=2.32.3)
Requires-Dist: configparser
